[{"street1":"W WHITTAKER ST","street2":"","city":"BOISE","state":"ID","zip":"83714","country":"US"},{"street1":"N LIBERTY ST","street2":"","city":"BOISE","state":"ID","zip":"83704","country":"US"},{"street1":"E YUCCA CANYON ST","street2":"","city":"MERIDIAN","state":"ID","zip":"83646","country":"US"},{"street1":"W ROCKFORD ST","street2":"","city":"MERIDIAN","state":"ID","zip":"83642","country":"US"},{"street1":"W WOLF RAPIDS ST","street2":"","city":"MERIDIAN","state":"ID","zip":"83646","country":"US"},{"street1":"W PETRIE ST","street2":"","city":"BOISE","state":"ID","zip":"83704","country":"US"},{"street1":"W JACKSNIPE DR","street2":"","city":"MERIDIAN","state":"ID","zip":"83642","country":"US"},{"street1":"W HOLBROOK AVE","street2":"","city":"BOISE","state":"ID","zip":"83704","country":"US"},{"street1":"E 47TH ST","street2":"","city":"GARDEN CITY","state":"ID","zip":"83714","country":"US"},{"street1":"S RUSHMORE WAY","street2":"","city":"BOISE","state":"ID","zip":"83709","country":"US"},{"street1":"E BLUE HERON ST","street2":"","city":"MERIDIAN","state":"ID","zip":"83646","country":"US"},{"street1":"S FIDDLE AVE","street2":"","city":"MERIDIAN","state":"ID","zip":"83642","country":"US"},{"street1":"W BIENAPFL DR","street2":"","city":"BOISE","state":"ID","zip":"83709","country":"US"},{"street1":"S NASTURTIUM PL","street2":"","city":"BOISE","state":"ID","zip":"83716","country":"US"},{"street1":"S STRAUGHAN AVE","street2":"","city":"BOISE","state":"ID","zip":"83712","country":"US"},{"street1":"S DANSKIN LN","street2":"","city":"MERIDIAN","state":"ID","zip":"83642","country":"US"},{"street1":"W CORY LN","street2":"","city":"BOISE","state":"ID","zip":"83704","country":"US"},{"street1":"N COOL SPRINGS AVE","street2":"","city":"KUNA","state":"ID","zip":"83634","country":"US"},{"street1":"N WHITE SPRUCE PL","street2":"","city":"BOISE","state":"ID","zip":"83713","country":"US"},{"street1":"W KOOTENAI ST","street2":"","city":"BOISE","state":"ID","zip":"83705","country":"US"},{"street1":"W DEVOTION DR","street2":"","city":"MERIDIAN","state":"ID","zip":"83642","country":"US"},{"street1":"W WATER GROVE DR","street2":"","city":"EAGLE","state":"ID","zip":"83616","country":"US"},{"street1":"S BURGDORF WAY","street2":"","city":"MERIDIAN","state":"ID","zip":"83642","country":"US"},{"street1":"N BEVERLY DR","street2":"","city":"EAGLE","state":"ID","zip":"83616","country":"US"},{"street1":"S TRAPPER COVE AVE","street2":"","city":"BOISE","state":"ID","zip":"83709","country":"US"},{"street1":"NW 11TH AVE","street2":"","city":"MERIDIAN","state":"ID","zip":"83646","country":"US"},{"street1":"E CADILLAC DR","street2":"","city":"MERIDIAN","state":"ID","zip":"83642","country":"US"},{"street1":"S ELM ST","street2":"","city":"BOISE","state":"ID","zip":"83712","country":"US"},{"street1":"N SHADOWRIDGE AVE","street2":"","city":"EAGLE","state":"ID","zip":"83616","country":"US"},{"street1":"E HOLLY ST","street2":"","city":"BOISE","state":"ID","zip":"83712","country":"US"},{"street1":"S CAPITOL BLVD","street2":"","city":"BOISE","state":"ID","zip":"83706","country":"US"},{"street1":"S MICHIGAN AVE","street2":"","city":"BOISE","state":"ID","zip":"83706","country":"US"},{"street1":"N TULLSHIRE WAY","street2":"","city":"EAGLE","state":"ID","zip":"83616","country":"US"},{"street1":"N ANFIELD AVE","street2":"","city":"MERIDIAN","state":"ID","zip":"83646","country":"US"},{"street1":"N GRANDEE ST","street2":"","city":"BOISE","state":"ID","zip":"83704","country":"US"},{"street1":"N HIGHFIELD WAY","street2":"","city":"BOISE","state":"ID","zip":"83714","country":"US"},{"street1":"N DEVON WAY","street2":"","city":"STAR","state":"ID","zip":"83669","country":"US"},{"street1":"W LEILANI DR","street2":"","city":"BOISE","state":"ID","zip":"83709","country":"US"},{"street1":"N ELSINORE AVE","street2":"","city":"MERIDIAN","state":"ID","zip":"83646","country":"US"},{"street1":"N MAPLE GROVE RD","street2":"","city":"BOISE","state":"ID","zip":"83704","country":"US"},{"street1":"W BARON LN","street2":"","city":"BOISE","state":"ID","zip":"83703","country":"US"},{"street1":"N PREDO WAY","street2":"","city":"MERIDIAN","state":"ID","zip":"83646","country":"US"},{"street1":"N ADDAX AVE","street2":"","city":"KUNA","state":"ID","zip":"83634","country":"US"},{"street1":"W LOS FLORES ST","street2":"","city":"MERIDIAN","state":"ID","zip":"83646","country":"US"},{"street1":"W CHRISTOPHER DR","street2":"","city":"MERIDIAN","state":"ID","zip":"83642","country":"US"},{"street1":"E MEADOW WOOD ST","street2":"","city":"MERIDIAN","state":"ID","zip":"83646","country":"US"},{"street1":"W CARTRIDGE ST","street2":"","city":"BOISE","state":"ID","zip":"83713","country":"US"},{"street1":"N 10TH ST","street2":"","city":"BOISE","state":"ID","zip":"83702","country":"US"},{"street1":"E VICTORY RD","street2":"BLDG M","city":"MERIDIAN","state":"ID","zip":"83642","country":"US"},{"street1":"S GATEWOOD LN","street2":"","city":"BOISE","state":"ID","zip":"83709","country":"US"},{"street1":"N GAVIOLA AVE","street2":"","city":"MERIDIAN","state":"ID","zip":"83646","country":"US"},{"street1":"N COLE RD","street2":"","city":"BOISE","state":"ID","zip":"83704","country":"US"},{"street1":"N SIMERLY AVE","street2":"","city":"MERIDIAN","state":"ID","zip":"83646","country":"US"},{"street1":"W ASHBY DR","street2":"BLDG B","city":"MERIDIAN","state":"ID","zip":"83646","country":"US"},{"street1":"E BLUE HERON LN","street2":"","city":"MERIDIAN","state":"ID","zip":"83646","country":"US"},{"street1":"S UPDALE AVE","street2":"","city":"KUNA","state":"ID","zip":"83634","country":"US"},{"street1":"W TANGO CREEK DR","street2":"","city":"MERIDIAN","state":"ID","zip":"83646","country":"US"},{"street1":"W SUSAN ST","street2":"","city":"BOISE","state":"ID","zip":"83704","country":"US"},{"street1":"N BURLEY WAY","street2":"","city":"MERIDIAN","state":"ID","zip":"83646","country":"US"},{"street1":"N MOUNTAIN LION AVE","street2":"","city":"STAR","state":"ID","zip":"83669","country":"US"},{"street1":"S DENVER AVE","street2":"","city":"BOISE","state":"ID","zip":"83706","country":"US"},{"street1":"S CONSTELLATION WAY","street2":"","city":"BOISE","state":"ID","zip":"83709","country":"US"},{"street1":"S MISSOULA WAY","street2":"","city":"BOISE","state":"ID","zip":"83709","country":"US"},{"street1":"W PERUGIA ST","street2":"BLDG S","city":"MERIDIAN","state":"ID","zip":"83642","country":"US"},{"street1":"W SAGEBRUSH ST","street2":"","city":"BOISE","state":"ID","zip":"83709","country":"US"},{"street1":"N ASPEN LAKES WAY","street2":"","city":"STAR","state":"ID","zip":"83669","country":"US"},{"street1":"W CHAMPAGNE CT","street2":"","city":"EAGLE","state":"ID","zip":"83616","country":"US"},{"street1":"S EUCLID LN","street2":"","city":"BOISE","state":"ID","zip":"83706","country":"US"},{"street1":"N SILVER SPRUCE AVE","street2":"","city":"MERIDIAN","state":"ID","zip":"83646","country":"US"},{"street1":"W GINGER CREEK DR","street2":"","city":"BOISE","state":"ID","zip":"83713","country":"US"},{"street1":"E PENNSYLVANIA ST","street2":"","city":"BOISE","state":"ID","zip":"83706","country":"US"},{"street1":"N LENA AVE","street2":"","city":"BOISE","state":"ID","zip":"83713","country":"US"},{"street1":"S LONGMOOR AVE","street2":"","city":"BOISE","state":"ID","zip":"83709","country":"US"},{"street1":"W GOLDENROD AVE","street2":"","city":"BOISE","state":"ID","zip":"83713","country":"US"},{"street1":"S CARBONDALE PL","street2":"","city":"MERIDIAN","state":"ID","zip":"83642","country":"US"},{"street1":"S ALLANTE PL","street2":"","city":"BOISE","state":"ID","zip":"83709","country":"US"},{"street1":"W BUTTE ST","street2":"","city":"BOISE","state":"ID","zip":"83704","country":"US"},{"street1":"E FLORENCE DR","street2":"","city":"MERIDIAN","state":"ID","zip":"83642","country":"US"},{"street1":"N MAIN ST","street2":"","city":"MERIDIAN","state":"ID","zip":"83642","country":"US"},{"street1":"W MORNIN MIST ST","street2":"","city":"BOISE","state":"ID","zip":"83709","country":"US"},{"street1":"E MENDOTA DR","street2":"","city":"BOISE","state":"ID","zip":"83716","country":"US"},{"street1":"W GREENBRIER DR","street2":"","city":"BOISE","state":"ID","zip":"83705","country":"US"},{"street1":"N LILYTURF AVE","street2":"","city":"MERIDIAN","state":"ID","zip":"83646","country":"US"},{"street1":"S COLERIDGE PL","street2":"","city":"BOISE","state":"ID","zip":"83706","country":"US"},{"street1":"E JEFFERSON ST","street2":"","city":"BOISE","state":"ID","zip":"83712","country":"US"},{"street1":"N SCHICKS RIDGE RD","street2":"","city":"BOISE","state":"ID","zip":"83714","country":"US"},{"street1":"W DENTON LN","street2":"","city":"BOISE","state":"ID","zip":"83704","country":"US"},{"street1":"N MORPHEUS AVE","street2":"","city":"MERIDIAN","state":"ID","zip":"83646","country":"US"},{"street1":"S MOONFLOWER PL","street2":"","city":"BOISE","state":"ID","zip":"83716","country":"US"},{"street1":"E BLACK HAWK CT","street2":"","city":"KUNA","state":"ID","zip":"83634","country":"US"},{"street1":"W TRAFALGER CT","street2":"","city":"BOISE","state":"ID","zip":"83709","country":"US"},{"street1":"E FLORENCE DR","street2":"","city":"MERIDIAN","state":"ID","zip":"83642","country":"US"},{"street1":"W CASSIA ST","street2":"","city":"BOISE","state":"ID","zip":"83705","country":"US"},{"street1":"N SNOW GOOSE WAY","street2":"","city":"MERIDIAN","state":"ID","zip":"83646","country":"US"},{"street1":"S FRANKLIN PARK DR","street2":"","city":"BOISE","state":"ID","zip":"83709","country":"US"},{"street1":"W TARGEE ST","street2":"","city":"BOISE","state":"ID","zip":"83705","country":"US"},{"street1":"W HOWE ST","street2":"","city":"BOISE","state":"ID","zip":"83706","country":"US"},{"street1":"W FAIRVIEW AVE","street2":"","city":"BOISE","state":"ID","zip":"83704","country":"US"},{"street1":"N CLOVERDALE RD","street2":"","city":"BOISE","state":"ID","zip":"83713","country":"US"},{"street1":"N 10TH AVE","street2":"","city":"BOISE","state":"ID","zip":"83714","country":"US"}]
